DESCRIPTION.rst
LICENSE
MANIFEST.in
README.rst
gigasetelements-cli.conf.template
setup.py
gigasetelements/__init__.py
gigasetelements/__main__.py
gigasetelements/gigasetelements.py
gigasetelements_cli.egg-info/PKG-INFO
gigasetelements_cli.egg-info/SOURCES.txt
gigasetelements_cli.egg-info/dependency_links.txt
gigasetelements_cli.egg-info/entry_points.txt
gigasetelements_cli.egg-info/requires.txt
gigasetelements_cli.egg-info/top_level.txt