Metadata-Version: 1.0
Name: gigasetelements-cli
Version: 1.3.7
Summary: gigasetelements-cli allows you to control your     Gigaset Elements home security system from the command line.
Home-page: https://github.com/dynasticorpheus/gigasetelements-cli
Author: dynasticorpheus
Author-email: dynasticorpheus@gmail.com
License: GPL2
Keywords: Home Automation,Home Security,Internet of Things (IoT)
Platform: UNKNOWN
Classifier: Development Status :: 4 - Beta
Classifier: Intended Audience :: End Users/Desktop
Classifier: Topic :: Software Development :: Build Tools
Classifier: License :: OSI Approved :: GNU General Public License v2 (GPLv2)
Classifier: Programming Language :: Python :: 2
Classifier: Programming Language :: Python :: 2.7
